piimp/__init__.py
piimp/esd/__init__.py
piimp/esd/config.py
piimp-0.0.0.dist-info/METADATA
piimp-0.0.0.dist-info/WHEEL
piimp-0.0.0.dist-info/top_level.txt
piimp-0.0.0.dist-info/RECORD
