Metadata-Version: 2.1
Name: piimp
Version: 0.0.0
Summary: This is a Python package for post-processing ice irradiation data.
Home-page: https://github.com/Cavenfish/PIIMP
Author: Brian C. Ferrari
Author-email: brian.ferrari@ucf.edu
License: UNKNOWN
Platform: UNKNOWN
Classifier: Programming Language :: Python :: 3
Classifier: License :: OSI Approved :: MIT License
Classifier: Operating System :: Microsoft :: Windows :: Windows 10
Requires-Dist: numpy
Requires-Dist: scipy
Requires-Dist: pandas
Requires-Dist: openpyxl
Requires-Dist: matplotlib
Requires-Dist: xlrd
Requires-Dist: xlsxwriter
Requires-Dist: sklearn
Requires-Dist: collections
Requires-Dist: seabornglob
